const.py
logger.py
script.py
django_venv-1.0.0.data/scripts/README.md
django_venv-1.0.0.data/scripts/const.py
django_venv-1.0.0.data/scripts/database
django_venv-1.0.0.data/scripts/django-setup
django_venv-1.0.0.data/scripts/django-venv
django_venv-1.0.0.data/scripts/logger.py
django_venv-1.0.0.data/scripts/script.py
django_venv-1.0.0.dist-info/LICENSE
django_venv-1.0.0.dist-info/METADATA
django_venv-1.0.0.dist-info/WHEEL
django_venv-1.0.0.dist-info/top_level.txt
django_venv-1.0.0.dist-info/RECORD
