Metadata-Version: 2.1
Name: django-venv
Version: 1.0.0
Home-page: https://github.com/GianlucaIavicoli/Django-Setup
Author: Gianluca Iavicoli
Author-email: gianluca.iavicoli04@gmail.com
License: Apache License 2.0
Project-URL: Source Code, https://github.com/GianlucaIavicoli/Django-Venv
Keywords: django django-environment mysql postgres cassandra scylla docker
Classifier: Development Status :: 3 - Alpha
Classifier: Intended Audience :: Developers
Classifier: License :: OSI Approved :: Apache Software License
Classifier: Programming Language :: Python :: 3
Requires-Python: >=3.8
License-File: LICENSE
Requires-Dist: django
Requires-Dist: mysqlclient
Requires-Dist: colorlog
Requires-Dist: sqlparse
Requires-Dist: asgiref
Requires-Dist: tomli
Requires-Dist: yapf
Requires-Dist: zipp
Requires-Dist: platformdirs
Requires-Dist: importlib-metadata
Requires-Dist: ast-comments
